sqre_uservice_metricdeviation-0.0.5.dist-info/DESCRIPTION.rst
sqre_uservice_metricdeviation-0.0.5.dist-info/METADATA
sqre_uservice_metricdeviation-0.0.5.dist-info/RECORD
sqre_uservice_metricdeviation-0.0.5.dist-info/WHEEL
sqre_uservice_metricdeviation-0.0.5.dist-info/entry_points.txt
sqre_uservice_metricdeviation-0.0.5.dist-info/metadata.json
sqre_uservice_metricdeviation-0.0.5.dist-info/top_level.txt
uservice_metricdeviation/__init__.py
uservice_metricdeviation/server.py
