Metadata-Version: 2.0
Name: sqre-uservice-metricdeviation
Version: 0.0.5
Summary: Minimal SQuaRE API wrapper for QA metrics
Home-page: https://github.com/lsst-sqre/sqre-uservice-metricdeviation
Author: Adam Thornton
Author-email: athornton@lsst.org
License: MIT
Keywords: lsst
Platform: UNKNOWN
Classifier: Development Status :: 4 - Beta
Classifier: Programming Language :: Python :: 2.7
Classifier: Programming Language :: Python :: 3.5
Classifier: License :: OSI Approved :: MIT License
Requires-Dist: bitly-oauth2-proxy-session (==0.1.4)
Requires-Dist: sqre-apikit (==0.0.10)
